palletier/__init__.py
palletier/box.py
palletier/cli.py
palletier/packedpallet.py
palletier/packer.py
palletier/pallet.py
palletier/palletier.py
palletier/topology.py
palletier-0.1.0.dist-info/DESCRIPTION.rst
palletier-0.1.0.dist-info/METADATA
palletier-0.1.0.dist-info/RECORD
palletier-0.1.0.dist-info/WHEEL
palletier-0.1.0.dist-info/entry_points.txt
palletier-0.1.0.dist-info/metadata.json
palletier-0.1.0.dist-info/top_level.txt
