Metadata-Version: 2.0
Name: palletier
Version: 0.1.0
Summary: Palletier is a Python implementation of the solution for the distributer's pallet packing problem
Home-page: https://github.com/alanbato/palletier
Author: Alan Velasco
Author-email: alanvelasco.a@gmail.com
License: MIT license
Keywords: palletier
Platform: UNKNOWN
Classifier: Development Status :: 2 - Pre-Alpha
Classifier: Intended Audience :: Developers
Classifier: License :: OSI Approved :: MIT License
Classifier: Natural Language :: English
Classifier: Programming Language :: Python :: 2
Classifier: Programming Language :: Python :: 2.7
Classifier: Programming Language :: Python :: 3
Classifier: Programming Language :: Python :: 3.4
Classifier: Programming Language :: Python :: 3.5
Classifier: Programming Language :: Python :: 3.6
Requires-Dist: Click (>=6.0)
